bigsuds.py
setup.cfg
setup.py
bigsuds.egg-info/PKG-INFO
bigsuds.egg-info/SOURCES.txt
bigsuds.egg-info/dependency_links.txt
bigsuds.egg-info/requires.txt
bigsuds.egg-info/top_level.txt