Metadata-Version: 1.1
Name: bigsuds
Version: 1.0.5
Summary: Library for F5 Networks iControl API
Home-page: http://devcentral.f5.com
Author: F5 Networks, Inc.
Author-email: devcentral@f5.com
License: https://devcentral.f5.com/resources/devcentral-eula
Keywords: f5 icontrol
Platform: UNKNOWN
Classifier: Development Status :: 5 - Production/Stable
Classifier: Intended Audience :: Developers
Classifier: Programming Language :: Python :: 2
Classifier: Programming Language :: Python :: 2.4
Classifier: Programming Language :: Python :: 2.5
Classifier: Programming Language :: Python :: 2.6
Classifier: Programming Language :: Python :: 2.7
Classifier: Programming Language :: Python :: 3.5
Classifier: Programming Language :: Python :: 3.6
